psycopg2_extension/__init__.py
psycopg2_extension/base_command.py
psycopg2_extension/patch_database_creation.py
psycopg2_extension/utils.py
psycopg2_extension/management/__init__.py
psycopg2_extension/management/commands/__init__.py
psycopg2_extension/management/commands/psqlclean.py
psycopg2_extension/management/commands/psqlinit.py
psycopg2_extension/management/commands/psqlsnapshot.py
skip_django_psycopg2_extension-0.2.0.dist-info/LICENSE
skip_django_psycopg2_extension-0.2.0.dist-info/METADATA
skip_django_psycopg2_extension-0.2.0.dist-info/WHEEL
skip_django_psycopg2_extension-0.2.0.dist-info/top_level.txt
skip_django_psycopg2_extension-0.2.0.dist-info/RECORD
