Metadata-Version: 2.1
Name: skip-django-psycopg2-extension
Version: 0.2.0
Summary: Library contains django commands which helps to prepare and manage PostgreSQL database.
Home-page: https://github.com/skip-pay/django-psycopg2-extension
License: MIT
Classifier: Development Status :: 3 - Alpha
Classifier: Framework :: Django
Classifier: Intended Audience :: Developers
Classifier: License :: OSI Approved :: BSD License
Classifier: Operating System :: OS Independent
Classifier: Programming Language :: Python
Classifier: Topic :: Internet :: WWW/HTTP
License-File: LICENSE
Requires-Dist: django >=4.2
